{"LOO3SERA00": ["LOO3SERA00", "Production or transportation", "Loop 3 Series A", "RMR", "/media/emme/0B/DATA/rmr/processed/21_lv3/Loop 3 Series A/mp3/LV3_A_ 1-item_0.mp3", {"duration": "77.0863", "sample_rate": "44100", "sample_count": "3399505.00", "channels": "2", "bit_resolution": "16", "max_volume": "-2.5438", "mean_rms": "4186.0000", "tags_mtt": [["ambient", "0.3295"], ["weird", "0.1577"], ["slow", "0.1279"], ["electronic", "0.0933"], ["synth", "0.0772"], ["quiet", "0.0672"], ["loud", "0.0565"], ["no vocals", "0.0504"], ["techno", "0.0463"]], "tags_msd": [["ambient", "0.4171"], ["electronic", "0.2473"], ["experimental", "0.2338"], ["instrumental", "0.0979"], ["electronica", "0.0690"], ["rock", "0.0637"], ["metal", "0.0469"], ["chillout", "0.0462"], ["indie", "0.0400"]], "comp_mtt": [["choir", "0.1472"], ["male", "0.1359"], ["ambient", "0.3113"], ["male", "0.1126"], ["ambient", "0.2882"], ["ambient", "0.4126"], ["ambient", "0.4974"], ["ambient", "0.3767"], ["ambient", "0.4875"], ["slow", "0.2485"], ["ambient", "0.4532"], ["ambient", "0.3745"], ["ambient", "0.5318"], ["ambient", "0.4232"], ["ambient", "0.4325"], ["ambient", "0.4106"], ["ambient", "0.4154"], ["ambient", "0.3721"], ["ambient", "0.3336"], ["ambient", "0.3395"], ["ambient", "0.3521"], ["loud", "0.2709"], ["ambient", "0.2757"], ["loud", "0.2631"], ["ambient", "0.3444"]], "comp_msd": [["electronic", "0.1667"], ["ambient", "0.2522"], ["ambient", "0.3477"], ["ambient", "0.2397"], ["ambient", "0.3137"], ["ambient", "0.4907"], ["ambient", "0.4755"], ["ambient", "0.4904"], ["ambient", "0.5826"], ["jazz", "0.2884"], ["ambient", "0.5826"], ["ambient", "0.5371"], ["ambient", "0.5290"], ["ambient", "0.4504"], ["ambient", "0.6567"], ["ambient", "0.6356"], ["ambient", "0.5377"], ["ambient", "0.4261"], ["ambient", "0.3650"], ["ambient", "0.2983"], ["ambient", "0.4460"], ["ambient", "0.3681"], ["experimental", "0.3679"], ["experimental", "0.4176"], ["ambient", "0.3439"]]}], "LOO3SERA01": ["LOO3SERA01", "We need these marble floors and the sensation of flow", "Loop 3 Series A", "RMR", "/media/emme/0B/DATA/rmr/processed/21_lv3/Loop 3 Series A/mp3/LV3_A_ 2-item_2.mp3", {"duration": "77.0863", "sample_rate": "44100", "sample_count": "3399505.00", "channels": "2", "bit_resolution": "16", "max_volume": "-2.4656", "mean_rms": "8252.0000", "tags_mtt": [["ambient", "0.1850"], ["loud", "0.1292"], ["weird", "0.1203"], ["rock", "0.1156"], ["electronic", "0.0975"], ["techno", "0.0767"], ["slow", "0.0697"], ["drums", "0.0677"], ["synth", "0.0580"]], "tags_msd": [["experimental", "0.2919"], ["ambient", "0.2457"], ["electronic", "0.1962"], ["rock", "0.1075"], ["metal", "0.0796"], ["indie", "0.0795"], ["instrumental", "0.0785"], ["alternative", "0.0600"], ["punk", "0.0577"]], "comp_mtt": [["ambient", "0.2724"], ["ambient", "0.2731"], ["ambient", "0.2648"], ["ambient", "0.3663"], ["ambient", "0.4043"], ["ambient", "0.5535"], ["ambient", "0.2807"], ["rock", "0.3711"], ["ambient", "0.1921"], ["rock", "0.1926"], ["ambient", "0.2763"], ["ambient", "0.2535"], ["rock", "0.2559"], ["loud", "0.2226"], ["rock", "0.1842"], ["loud", "0.2744"], ["loud", "0.2328"], ["loud", "0.2032"], ["loud", "0.1782"], ["loud", "0.1254"], ["loud", "0.0980"], ["loud", "0.0958"], ["rock", "0.1232"], ["rock", "0.1568"], ["electronic", "0.2086"]], "comp_msd": [["ambient", "0.2909"], ["ambient", "0.3197"], ["ambient", "0.2398"], ["ambient", "0.4654"], ["ambient", "0.5276"], ["ambient", "0.4994"], ["ambient", "0.2639"], ["experimental", "0.2883"], ["ambient", "0.2850"], ["experimental", "0.3444"], ["ambient", "0.3592"], ["ambient", "0.3593"], ["experimental", "0.4144"], ["experimental", "0.3832"], ["experimental", "0.3286"], ["experimental", "0.3882"], ["experimental", "0.3949"], ["experimental", "0.3408"], ["ambient", "0.2335"], ["experimental", "0.3019"], ["experimental", "0.2655"], ["experimental", "0.3130"], ["experimental", "0.2880"], ["experimental", "0.2561"], ["electronic", "0.2971"]]}], "LOO3SERA02": ["LOO3SERA02", "A third enlightenment is summoning forth spirit", "Loop 3 Series A", "RMR", "/media/emme/0B/DATA/rmr/processed/21_lv3/Loop 3 Series A/mp3/LV3_A_ 3-item_4.mp3", {"duration": "77.0863", "sample_rate": "44100", "sample_count": "3399505.00", "channels": "2", "bit_resolution": "16", "max_volume": "-3.7251", "mean_rms": "3705.0000", "tags_mtt": [["techno", "0.1719"], ["weird", "0.1631"], ["ambient", "0.1607"], ["drums", "0.1523"], ["electronic", "0.1408"], ["rock", "0.1140"], ["loud", "0.0813"], ["fast", "0.0711"], ["beat", "0.0653"]], "tags_msd": [["experimental", "0.2471"], ["metal", "0.2085"], ["ambient", "0.1914"], ["electronic", "0.1760"], ["rock", "0.0741"], ["punk", "0.0666"], ["instrumental", "0.0601"], ["electronica", "0.0520"], ["heavy metal", "0.0363"]], "comp_mtt": [["drums", "0.1471"], ["metal", "0.2402"], ["rock", "0.2897"], ["loud", "0.1730"], ["rock", "0.2851"], ["rock", "0.2943"], ["weird", "0.2054"], ["ambient", "0.2697"], ["ambient", "0.3154"], ["ambient", "0.3548"], ["ambient", "0.2879"], ["ambient", "0.3320"], ["ambient", "0.3522"], ["ambient", "0.3055"], ["weird", "0.2406"], ["drums", "0.3577"], ["drums", "0.3252"], ["drums", "0.2978"], ["techno", "0.4306"], ["rock", "0.2283"], ["techno", "0.5553"], ["techno", "0.3598"], ["techno", "0.3782"], ["drums", "0.4398"], ["drums", "0.3190"]], "comp_msd": [["metal", "0.4003"], ["metal", "0.4429"], ["metal", "0.3699"], ["ambient", "0.3791"], ["ambient", "0.3203"], ["metal", "0.4186"], ["metal", "0.3620"], ["metal", "0.3426"], ["experimental", "0.2879"], ["experimental", "0.3201"], ["experimental", "0.3189"], ["experimental", "0.2873"], ["ambient", "0.3957"], ["experimental", "0.2997"], ["metal", "0.2183"], ["metal", "0.2383"], ["electronic", "0.3965"], ["ambient", "0.3289"], ["metal", "0.4263"], ["metal", "0.2798"], ["experimental", "0.2912"], ["Hip-Hop", "0.3114"], ["electronic", "0.3842"], ["electronic", "0.2269"], ["electronic", "0.3441"]]}], "LOO3SERA03": ["LOO3SERA03", "Knack for sports and compassion", "Loop 3 Series A", "RMR", "/media/emme/0B/DATA/rmr/processed/21_lv3/Loop 3 Series A/mp3/LV3_A_ 4-item_5.mp3", {"duration": "77.0863", "sample_rate": "44100", "sample_count": "3399505.00", "channels": "2", "bit_resolution": "16", "max_volume": "-3.0311", "mean_rms": "6487.0000", "tags_mtt": [["ambient", "0.1931"], ["weird", "0.1735"], ["electronic", "0.1183"], ["techno", "0.1112"], ["loud", "0.0979"], ["rock", "0.0649"], ["drums", "0.0632"], ["synth", "0.0631"], ["slow", "0.0464"]], "tags_msd": [["experimental", "0.3320"], ["electronic", "0.3087"], ["ambient", "0.3084"], ["metal", "0.1294"], ["electronica", "0.0844"], ["instrumental", "0.0677"], ["rock", "0.0644"], ["indie", "0.0476"], ["alternative", "0.0442"]], "comp_mtt": [["electronic", "0.1699"], ["ambient", "0.2161"], ["ambient", "0.2136"], ["ambient", "0.2346"], ["ambient", "0.2306"], ["ambient", "0.2786"], ["ambient", "0.2390"], ["ambient", "0.1717"], ["ambient", "0.1282"], ["weird", "0.1379"], ["loud", "0.2162"], ["weird", "0.1655"], ["weird", "0.1935"], ["weird", "0.2099"], ["weird", "0.1878"], ["techno", "0.2743"], ["weird", "0.2692"], ["techno", "0.2217"], ["weird", "0.2482"], ["weird", "0.2175"], ["loud", "0.1966"], ["weird", "0.1814"], ["ambient", "0.2963"], ["ambient", "0.4265"], ["ambient", "0.3014"]], "comp_msd": [["experimental", "0.4348"], ["experimental", "0.3731"], ["ambient", "0.3263"], ["ambient", "0.2942"], ["ambient", "0.3261"], ["ambient", "0.3137"], ["metal", "0.2792"], ["metal", "0.3538"], ["metal", "0.3580"], ["metal", "0.5743"], ["metal", "0.5155"], ["ambient", "0.3702"], ["electronic", "0.3915"], ["electronic", "0.4028"], ["electronic", "0.3559"], ["electronic", "0.4451"], ["experimental", "0.3881"], ["electronic", "0.4789"], ["electronic", "0.4944"], ["electronic", "0.4587"], ["electronic", "0.4563"], ["electronic", "0.3916"], ["ambient", "0.4565"], ["experimental", "0.5197"], ["electronic", "0.4587"]]}], "LOO3SERA04": ["LOO3SERA04", "On the digital realm both benefits and suffers", "Loop 3 Series A", "RMR", "/media/emme/0B/DATA/rmr/processed/21_lv3/Loop 3 Series A/mp3/LV3_A_ 5-item_6.mp3", {"duration": "77.0863", "sample_rate": "44100", "sample_count": "3399505.00", "channels": "2", "bit_resolution": "16", "max_volume": "-5.4091", "mean_rms": "3099.0000", "tags_mtt": [["ambient", "0.2456"], ["weird", "0.1962"], ["electronic", "0.1604"], ["techno", "0.1383"], ["synth", "0.0863"], ["slow", "0.0808"], ["drums", "0.0721"], ["no vocals", "0.0609"], ["loud", "0.0573"]], "tags_msd": [["ambient", "0.3519"], ["experimental", "0.2662"], ["electronic", "0.2096"], ["metal", "0.1044"], ["instrumental", "0.0884"], ["rock", "0.0787"], ["electronica", "0.0578"], ["punk", "0.0432"], ["alternative", "0.0400"]], "comp_mtt": [["ambient", "0.2168"], ["ambient", "0.2650"], ["ambient", "0.1798"], ["ambient", "0.3572"], ["ambient", "0.1712"], ["slow", "0.2050"], ["ambient", "0.1877"], ["ambient", "0.1613"], ["ambient", "0.2517"], ["ambient", "0.2691"], ["ambient", "0.2821"], ["ambient", "0.2901"], ["ambient", "0.3280"], ["ambient", "0.2486"], ["techno", "0.3705"], ["ambient", "0.2876"], ["ambient", "0.3141"], ["ambient", "0.2854"], ["ambient", "0.2269"], ["weird", "0.2663"], ["ambient", "0.2597"], ["weird", "0.2453"], ["weird", "0.2504"], ["weird", "0.2625"], ["ambient", "0.1540"]], "comp_msd": [["electronic", "0.3414"], ["metal", "0.4103"], ["metal", "0.4865"], ["ambient", "0.3196"], ["experimental", "0.1828"], ["rock", "0.1848"], ["ambient", "0.2788"], ["experimental", "0.2168"], ["experimental", "0.2604"], ["ambient", "0.3964"], ["ambient", "0.3914"], ["ambient", "0.3665"], ["ambient", "0.3773"], ["ambient", "0.4129"], ["ambient", "0.4986"], ["ambient", "0.5629"], ["ambient", "0.4217"], ["ambient", "0.5218"], ["ambient", "0.4546"], ["ambient", "0.4184"], ["ambient", "0.4820"], ["experimental", "0.3978"], ["ambient", "0.3970"], ["ambient", "0.5217"], ["experimental", "0.2686"]]}], "LOO3SERA05": ["LOO3SERA05", "Unwavering commitment to ethics and truth", "Loop 3 Series A", "RMR", "/media/emme/0B/DATA/rmr/processed/21_lv3/Loop 3 Series A/mp3/LV3_A_ 6-item_7.mp3", {"duration": "77.0863", "sample_rate": "44100", "sample_count": "3399505.00", "channels": "2", "bit_resolution": "16", "max_volume": "-0.2117", "mean_rms": "13249.0000", "tags_mtt": [["loud", "0.2004"], ["techno", "0.1799"], ["electronic", "0.1584"], ["weird", "0.1570"], ["ambient", "0.1304"], ["rock", "0.1168"], ["drums", "0.0966"], ["synth", "0.0856"], ["fast", "0.0559"]], "tags_msd": [["experimental", "0.3591"], ["electronic", "0.3591"], ["ambient", "0.2170"], ["electronica", "0.0898"], ["indie", "0.0873"], ["rock", "0.0704"], ["metal", "0.0613"], ["alternative", "0.0581"], ["instrumental", "0.0530"]], "comp_mtt": [["drums", "0.0807"], ["male", "0.0872"], ["ambient", "0.0903"], ["drums", "0.2723"], ["male", "0.3576"], ["loud", "0.3114"], ["rock", "0.3149"], ["techno", "0.1874"], ["ambient", "0.2149"], ["ambient", "0.3949"], ["weird", "0.2648"], ["techno", "0.3539"], ["loud", "0.4753"], ["loud", "0.5796"], ["loud", "0.4958"], ["loud", "0.4020"], ["loud", "0.3654"], ["loud", "0.3245"], ["loud", "0.2808"], ["loud", "0.2405"], ["techno", "0.2403"], ["techno", "0.4235"], ["electronic", "0.2301"], ["drums", "0.2655"], ["drums", "0.2868"]], "comp_msd": [["electronic", "0.2318"], ["experimental", "0.3196"], ["experimental", "0.1996"], ["electronic", "0.4057"], ["experimental", "0.2763"], ["electronic", "0.2912"], ["experimental", "0.2879"], ["experimental", "0.3190"], ["ambient", "0.3912"], ["ambient", "0.5526"], ["ambient", "0.4596"], ["experimental", "0.4100"], ["experimental", "0.5615"], ["experimental", "0.5355"], ["experimental", "0.5347"], ["experimental", "0.4796"], ["experimental", "0.5426"], ["electronic", "0.4557"], ["electronic", "0.4167"], ["electronic", "0.4822"], ["electronic", "0.4748"], ["electronic", "0.5023"], ["electronic", "0.5624"], ["electronic", "0.4974"], ["ambient", "0.4855"]]}], "LOO3SERAA06": ["LOO3SERAA06", "We only exist in a creatively individualized political culture", "Loop 3 Series AA", "RMR", "/media/emme/0B/DATA/rmr/processed/21_lv3/Loop 3 Series AA/mp3/LV3_AA_ 1-item_1.mp3", {"duration": "85.0798", "sample_rate": "44100", "sample_count": "3752018.00", "channels": "2", "bit_resolution": "16", "max_volume": "-0.8946", "mean_rms": "4582.0000", "tags_mtt": [["ambient", "0.1536"], ["electronic", "0.1528"], ["rock", "0.1490"], ["weird", "0.1429"], ["techno", "0.1356"], ["guitar", "0.0957"], ["loud", "0.0946"], ["synth", "0.0822"], ["drums", "0.0734"]], "tags_msd": [["experimental", "0.1949"], ["metal", "0.1670"], ["ambient", "0.1201"], ["punk", "0.1132"], ["rock", "0.1002"], ["electronic", "0.0986"], ["instrumental", "0.0634"], ["alternative", "0.0438"], ["indie", "0.0396"]], "comp_mtt": [["choir", "0.1945"], ["male", "0.1499"], ["ambient", "0.1537"], ["choir", "0.2108"], ["choir", "0.2874"], ["choir", "0.3145"], ["electronic", "0.1731"], ["ambient", "0.1170"], ["ambient", "0.1659"], ["electronic", "0.2482"], ["ambient", "0.2462"], ["ambient", "0.1420"], ["ambient", "0.2311"], ["ambient", "0.2132"], ["ambient", "0.2330"], ["electronic", "0.2853"], ["techno", "0.2306"], ["rock", "0.3352"], ["rock", "0.8119"], ["rock", "0.3203"], ["techno", "0.2576"], ["rock", "0.3857"], ["ambient", "0.1646"], ["rock", "0.2503"], ["rock", "0.4033"], ["electronic", "0.3116"], ["rock", "0.2340"], ["techno", "0.3599"]], "comp_msd": [["metal", "0.2795"], ["metal", "0.1647"], ["ambient", "0.3215"], ["ambient", "0.2863"], ["ambient", "0.1114"], ["experimental", "0.1713"], ["experimental", "0.2206"], ["ambient", "0.2367"], ["metal", "0.2859"], ["experimental", "0.2547"], ["experimental", "0.1233"], ["experimental", "0.2330"], ["experimental", "0.3041"], ["experimental", "0.3031"], ["metal", "0.2559"], ["experimental", "0.2889"], ["experimental", "0.2554"], ["experimental", "0.2182"], ["metal", "0.4062"], ["experimental", "0.1509"], ["punk", "0.4255"], ["punk", "0.2625"], ["punk", "0.2905"], ["punk", "0.4454"], ["metal", "0.3715"], ["experimental", "0.2333"], ["metal", "0.3085"], ["experimental", "0.2749"]]}], "LOO3SERAA07": ["LOO3SERAA07", "Future of mankind", "Loop 3 Series AA", "RMR", "/media/emme/0B/DATA/rmr/processed/21_lv3/Loop 3 Series AA/mp3/LV3_AA_ 2-item_2.mp3", {"duration": "85.0798", "sample_rate": "44100", "sample_count": "3752018.00", "channels": "2", "bit_resolution": "16", "max_volume": "-1.8746", "mean_rms": "6590.0000", "tags_mtt": [["rock", "0.1377"], ["loud", "0.1182"], ["male", "0.1089"], ["ambient", "0.1070"], ["weird", "0.0805"], ["electronic", "0.0716"], ["guitar", "0.0714"], ["slow", "0.0702"], ["drums", "0.0701"]], "tags_msd": [["experimental", "0.1875"], ["electronic", "0.1854"], ["metal", "0.1737"], ["ambient", "0.1532"], ["rock", "0.1068"], ["indie", "0.0528"], ["alternative", "0.0506"], ["electronica", "0.0504"], ["instrumental", "0.0497"]], "comp_mtt": [["rock", "0.1587"], ["ambient", "0.2232"], ["rock", "0.2056"], ["ambient", "0.1810"], ["rock", "0.4587"], ["rock", "0.6468"], ["ambient", "0.1072"], ["techno", "0.1554"], ["ambient", "0.2796"], ["drums", "0.2050"], ["ambient", "0.3755"], ["ambient", "0.2716"], ["slow", "0.1562"], ["classical", "0.2369"], ["opera", "0.2451"], ["male", "0.2196"], ["male", "0.3770"], ["male", "0.3107"], ["male", "0.3070"], ["male", "0.3262"], ["loud", "0.3211"], ["loud", "0.3152"], ["loud", "0.1870"], ["loud", "0.1999"], ["rock", "0.1952"], ["loud", "0.3491"], ["loud", "0.4580"], ["rock", "0.5141"]], "comp_msd": [["metal", "0.3847"], ["metal", "0.3844"], ["metal", "0.4829"], ["metal", "0.2896"], ["metal", "0.3954"], ["metal", "0.4540"], ["metal", "0.3934"], ["electronic", "0.4503"], ["electronic", "0.4958"], ["ambient", "0.4954"], ["electronic", "0.4731"], ["ambient", "0.5505"], ["experimental", "0.2402"], ["experimental", "0.2031"], ["jazz", "0.1941"], ["rock", "0.2048"], ["electronic", "0.1694"], ["rock", "0.1787"], ["electronic", "0.1899"], ["rock", "0.3183"], ["experimental", "0.2825"], ["experimental", "0.3005"], ["electronic", "0.3877"], ["experimental", "0.3487"], ["experimental", "0.2265"], ["metal", "0.2723"], ["experimental", "0.2667"], ["metal", "0.3853"]]}], "LOO3SERAA08": ["LOO3SERAA08", "Seek in the rearview mirror", "Loop 3 Series AA", "RMR", "/media/emme/0B/DATA/rmr/processed/21_lv3/Loop 3 Series AA/mp3/LV3_AA_ 3-item_3.mp3", {"duration": "85.0798", "sample_rate": "44100", "sample_count": "3752018.00", "channels": "2", "bit_resolution": "16", "max_volume": "-3.6497", "mean_rms": "4142.0000", "tags_mtt": [["ambient", "0.2360"], ["drums", "0.1846"], ["electronic", "0.1469"], ["rock", "0.1270"], ["weird", "0.1254"], ["techno", "0.1165"], ["slow", "0.1030"], ["synth", "0.0912"], ["beat", "0.0723"]], "tags_msd": [["experimental", "0.2253"], ["ambient", "0.1993"], ["electronic", "0.1812"], ["rock", "0.1272"], ["metal", "0.0973"], ["punk", "0.0772"], ["instrumental", "0.0755"], ["indie", "0.0723"], ["alternative", "0.0637"]], "comp_mtt": [["ambient", "0.2335"], ["ambient", "0.2286"], ["ambient", "0.3379"], ["ambient", "0.4068"], ["ambient", "0.4606"], ["ambient", "0.3905"], ["ambient", "0.4885"], ["rock", "0.5319"], ["drums", "0.2387"], ["rock", "0.3067"], ["rock", "0.3763"], ["rock", "0.5367"], ["drums", "0.2647"], ["techno", "0.4360"], ["drums", "0.5524"], ["drums", "0.4346"], ["drums", "0.3956"], ["rock", "0.4496"], ["electronic", "0.4567"], ["ambient", "0.3695"], ["rock", "0.3236"], ["ambient", "0.2819"], ["ambient", "0.3400"], ["ambient", "0.3487"], ["ambient", "0.3859"], ["ambient", "0.2240"], ["ambient", "0.2824"], ["ambient", "0.2928"]], "comp_msd": [["ambient", "0.2679"], ["ambient", "0.2794"], ["ambient", "0.3622"], ["ambient", "0.5060"], ["ambient", "0.3228"], ["ambient", "0.5053"], ["ambient", "0.6032"], ["electronic", "0.2920"], ["experimental", "0.1948"], ["metal", "0.3107"], ["rock", "0.2646"], ["metal", "0.2334"], ["electronic", "0.3187"], ["experimental", "0.2436"], ["metal", "0.1451"], ["experimental", "0.2079"], ["electronic", "0.2245"], ["indie", "0.3157"], ["punk", "0.3200"], ["experimental", "0.2989"], ["indie", "0.2522"], ["experimental", "0.2680"], ["experimental", "0.2664"], ["ambient", "0.2539"], ["experimental", "0.2307"], ["punk", "0.2256"], ["experimental", "0.2754"], ["experimental", "0.2476"]]}], "LOO3SERAA09": ["LOO3SERAA09", "Future as the ultimate source of life as immanence", "Loop 3 Series AA", "RMR", "/media/emme/0B/DATA/rmr/processed/21_lv3/Loop 3 Series AA/mp3/LV3_AA_ 4-item_4.mp3", {"duration": "85.0798", "sample_rate": "44100", "sample_count": "3752018.00", "channels": "2", "bit_resolution": "16", "max_volume": "-3.5826", "mean_rms": "4645.0000", "tags_mtt": [["rock", "0.2103"], ["techno", "0.1820"], ["weird", "0.1749"], ["loud", "0.1414"], ["ambient", "0.1350"], ["drums", "0.1321"], ["electronic", "0.1312"], ["metal", "0.0989"], ["fast", "0.0808"]], "tags_msd": [["metal", "0.2738"], ["experimental", "0.2302"], ["electronic", "0.1952"], ["ambient", "0.1952"], ["rock", "0.0731"], ["instrumental", "0.0588"], ["electronica", "0.0546"], ["punk", "0.0473"], ["heavy metal", "0.0406"]], "comp_mtt": [["drums", "0.3662"], ["drums", "0.2740"], ["ambient", "0.3005"], ["ambient", "0.2440"], ["ambient", "0.3038"], ["techno", "0.1983"], ["drums", "0.3447"], ["rock", "0.6161"], ["rock", "0.2736"], ["techno", "0.3512"], ["techno", "0.3567"], ["weird", "0.2359"], ["techno", "0.2839"], ["weird", "0.2516"], ["weird", "0.2427"], ["weird", "0.1833"], ["rock", "0.2420"], ["rock", "0.2238"], ["weird", "0.2405"], ["weird", "0.2373"], ["drums", "0.1787"], ["techno", "0.3580"], ["rock", "0.5671"], ["rock", "0.4113"], ["rock", "0.3815"], ["rock", "0.5690"], ["techno", "0.3981"], ["rock", "0.2302"]], "comp_msd": [["ambient", "0.3152"], ["ambient", "0.3344"], ["ambient", "0.3707"], ["ambient", "0.3015"], ["metal", "0.2399"], ["metal", "0.3056"], ["experimental", "0.2880"], ["metal", "0.4214"], ["metal", "0.3546"], ["experimental", "0.3038"], ["experimental", "0.3237"], ["experimental", "0.3205"], ["ambient", "0.2846"], ["metal", "0.5281"], ["metal", "0.5497"], ["metal", "0.4506"], ["metal", "0.4430"], ["metal", "0.3892"], ["metal", "0.3791"], ["experimental", "0.2357"], ["electronic", "0.4293"], ["electronic", "0.3724"], ["experimental", "0.2623"], ["electronic", "0.3573"], ["electronic", "0.3575"], ["electronic", "0.3641"], ["electronic", "0.3628"], ["experimental", "0.1943"]]}], "LOO3SERAA10": ["LOO3SERAA10", "The values embedded in technical artifacts", "Loop 3 Series AA", "RMR", "/media/emme/0B/DATA/rmr/processed/21_lv3/Loop 3 Series AA/mp3/LV3_AA_ 5-item_6.mp3", {"duration": "85.0798", "sample_rate": "44100", "sample_count": "3752018.00", "channels": "2", "bit_resolution": "16", "max_volume": "-5.7189", "mean_rms": "2210.0000", "tags_mtt": [["rock", "0.1719"], ["drums", "0.1647"], ["metal", "0.1218"], ["ambient", "0.1196"], ["weird", "0.0959"], ["guitar", "0.0855"], ["quiet", "0.0630"], ["fast", "0.0597"], ["loud", "0.0591"]], "tags_msd": [["metal", "0.2349"], ["experimental", "0.2220"], ["ambient", "0.1921"], ["electronic", "0.1397"], ["rock", "0.0891"], ["instrumental", "0.0735"], ["punk", "0.0443"], ["heavy metal", "0.0436"], ["electronica", "0.0398"]], "comp_mtt": [["drums", "0.1592"], ["metal", "0.2113"], ["metal", "0.2393"], ["metal", "0.1283"], ["rock", "0.7338"], ["rock", "0.5856"], ["rock", "0.6636"], ["rock", "0.5548"], ["weird", "0.2497"], ["drums", "0.3913"], ["ambient", "0.1838"], ["drums", "0.2075"], ["ambient", "0.2955"], ["ambient", "0.2678"], ["ambient", "0.2536"], ["ambient", "0.2093"], ["ambient", "0.1439"], ["drums", "0.1911"], ["quiet", "0.2345"], ["drums", "0.2476"], ["drums", "0.1691"], ["drums", "0.2619"], ["drums", "0.2959"], ["quiet", "0.2131"], ["drums", "0.3020"], ["ambient", "0.2374"], ["drums", "0.2933"], ["opera", "0.2967"]], "comp_msd": [["metal", "0.3748"], ["metal", "0.4108"], ["metal", "0.3597"], ["metal", "0.3065"], ["metal", "0.4518"], ["metal", "0.3428"], ["metal", "0.3329"], ["metal", "0.4976"], ["metal", "0.2954"], ["metal", "0.2552"], ["ambient", "0.2989"], ["experimental", "0.3039"], ["metal", "0.3513"], ["ambient", "0.2735"], ["ambient", "0.2810"], ["metal", "0.3188"], ["experimental", "0.2664"], ["experimental", "0.2887"], ["ambient", "0.3595"], ["experimental", "0.2920"], ["metal", "0.2397"], ["experimental", "0.2992"], ["experimental", "0.2149"], ["experimental", "0.2998"], ["experimental", "0.2566"], ["ambient", "0.2681"], ["jazz", "0.2433"], ["rock", "0.1671"]]}], "LOO3SERAA11": ["LOO3SERAA11", "Human future rooted in thinking", "Loop 3 Series AA", "RMR", "/media/emme/0B/DATA/rmr/processed/21_lv3/Loop 3 Series AA/mp3/LV3_AA_ 6-item_7.mp3", {"duration": "85.0798", "sample_rate": "44100", "sample_count": "3752018.00", "channels": "2", "bit_resolution": "16", "max_volume": "-0.7469", "mean_rms": "12219.0000", "tags_mtt": [["loud", "0.3700"], ["rock", "0.3342"], ["techno", "0.2116"], ["drums", "0.1835"], ["metal", "0.1501"], ["electronic", "0.1418"], ["fast", "0.1227"], ["weird", "0.1213"], ["guitar", "0.1177"]], "tags_msd": [["experimental", "0.3050"], ["electronic", "0.2927"], ["metal", "0.1830"], ["ambient", "0.1464"], ["rock", "0.0906"], ["electronica", "0.0832"], ["indie", "0.0665"], ["instrumental", "0.0622"], ["alternative", "0.0541"]], "comp_mtt": [["techno", "0.3535"], ["rock", "0.4674"], ["loud", "0.5817"], ["loud", "0.5069"], ["loud", "0.4622"], ["rock", "0.5299"], ["rock", "0.4102"], ["techno", "0.4211"], ["techno", "0.2250"], ["techno", "0.4939"], ["techno", "0.3825"], ["rock", "0.3331"], ["drums", "0.3923"], ["drums", "0.5399"], ["drums", "0.5949"], ["techno", "0.3894"], ["drums", "0.2097"], ["rock", "0.3594"], ["loud", "0.7471"], ["loud", "0.7505"], ["loud", "0.7509"], ["loud", "0.7868"], ["loud", "0.7881"], ["loud", "0.7880"], ["loud", "0.7215"], ["loud", "0.5521"], ["rock", "0.3919"], ["techno", "0.2698"]], "comp_msd": [["electronic", "0.4196"], ["electronic", "0.4253"], ["metal", "0.4910"], ["metal", "0.6423"], ["metal", "0.4434"], ["metal", "0.4238"], ["electronic", "0.3212"], ["experimental", "0.3917"], ["electronic", "0.4651"], ["electronic", "0.4684"], ["electronic", "0.4722"], ["electronic", "0.4348"], ["electronic", "0.4996"], ["electronic", "0.4572"], ["ambient", "0.5006"], ["electronic", "0.5215"], ["electronic", "0.4923"], ["electronic", "0.2599"], ["metal", "0.4487"], ["metal", "0.6504"], ["metal", "0.3261"], ["indie", "0.2519"], ["experimental", "0.2592"], ["experimental", "0.4089"], ["experimental", "0.4203"], ["experimental", "0.3638"], ["electronic", "0.2591"], ["electronic", "0.3115"]]}], "LOO3SERB12": ["LOO3SERB12", "Human story", "Loop 3 Series B", "RMR", "/media/emme/0B/DATA/rmr/processed/21_lv3/Loop 3 Series B/mp3/LV3_B_ 1-item_0.mp3", {"duration": "77.0863", "sample_rate": "44100", "sample_count": "3399505.00", "channels": "2", "bit_resolution": "16", "max_volume": "-1.0037", "mean_rms": "3304.0000", "tags_mtt": [["drums", "0.1740"], ["ambient", "0.1323"], ["quiet", "0.1302"], ["rock", "0.0937"], ["slow", "0.0891"], ["electronic", "0.0782"], ["techno", "0.0700"], ["weird", "0.0679"], ["guitar", "0.0620"]], "tags_msd": [["experimental", "0.1907"], ["rock", "0.1641"], ["metal", "0.1615"], ["electronic", "0.1463"], ["ambient", "0.1284"], ["alternative", "0.0725"], ["instrumental", "0.0691"], ["indie", "0.0659"], ["jazz", "0.0515"]], "comp_mtt": [["drums", "0.1850"], ["ambient", "0.1678"], ["weird", "0.1166"], ["rock", "0.4068"], ["drums", "0.4065"], ["drums", "0.3418"], ["rock", "0.1959"], ["drums", "0.3872"], ["drums", "0.2937"], ["rock", "0.3303"], ["drums", "0.3428"], ["drums", "0.2888"], ["quiet", "0.3762"], ["quiet", "0.2349"], ["quiet", "0.3091"], ["drums", "0.3250"], ["quiet", "0.3127"], ["ambient", "0.2062"], ["quiet", "0.1887"], ["quiet", "0.2610"], ["quiet", "0.2885"], ["rock", "0.3655"], ["guitar", "0.3051"], ["quiet", "0.2082"], ["electronic", "0.2350"]], "comp_msd": [["rock", "0.1839"], ["metal", "0.4312"], ["metal", "0.3126"], ["metal", "0.5967"], ["experimental", "0.2170"], ["metal", "0.5202"], ["metal", "0.2924"], ["experimental", "0.2716"], ["metal", "0.5998"], ["rock", "0.2538"], ["experimental", "0.2487"], ["experimental", "0.2162"], ["experimental", "0.2149"], ["rock", "0.2019"], ["experimental", "0.2721"], ["electronic", "0.2736"], ["experimental", "0.2843"], ["electronic", "0.2867"], ["experimental", "0.2243"], ["experimental", "0.2498"], ["ambient", "0.2402"], ["rock", "0.3709"], ["rock", "0.2907"], ["experimental", "0.1962"], ["electronic", "0.2125"]]}], "LOO3SERB13": ["LOO3SERB13", "Increasingly complex and comprehensive understanding of the other hand", "Loop 3 Series B", "RMR", "/media/emme/0B/DATA/rmr/processed/21_lv3/Loop 3 Series B/mp3/LV3_B_ 2-item_2.mp3", {"duration": "77.0863", "sample_rate": "44100", "sample_count": "3399505.00", "channels": "2", "bit_resolution": "16", "max_volume": "-3.3087", "mean_rms": "3819.0000", "tags_mtt": [["ambient", "0.3402"], ["electronic", "0.1558"], ["techno", "0.1553"], ["weird", "0.1489"], ["slow", "0.1039"], ["synth", "0.0966"], ["rock", "0.0565"], ["drums", "0.0541"], ["loud", "0.0527"]], "tags_msd": [["ambient", "0.3219"], ["electronic", "0.1982"], ["experimental", "0.1750"], ["rock", "0.1057"], ["instrumental", "0.0851"], ["electronica", "0.0560"], ["metal", "0.0531"], ["alternative", "0.0513"], ["indie", "0.0493"]], "comp_mtt": [["ambient", "0.2208"], ["ambient", "0.4938"], ["ambient", "0.5920"], ["ambient", "0.5782"], ["ambient", "0.5737"], ["ambient", "0.5290"], ["ambient", "0.2250"], ["ambient", "0.5532"], ["ambient", "0.5672"], ["ambient", "0.5778"], ["ambient", "0.5851"], ["ambient", "0.4611"], ["ambient", "0.3713"], ["ambient", "0.3938"], ["ambient", "0.4408"], ["techno", "0.6002"], ["techno", "0.3736"], ["ambient", "0.2936"], ["techno", "0.4378"], ["techno", "0.2488"], ["techno", "0.4368"], ["rock", "0.3750"], ["rock", "0.2565"], ["loud", "0.2558"], ["male", "0.2340"]], "comp_msd": [["ambient", "0.3746"], ["ambient", "0.5012"], ["ambient", "0.5190"], ["ambient", "0.4308"], ["ambient", "0.5331"], ["ambient", "0.3554"], ["electronic", "0.2015"], ["ambient", "0.4833"], ["ambient", "0.5517"], ["ambient", "0.5324"], ["ambient", "0.5994"], ["ambient", "0.5278"], ["ambient", "0.3731"], ["ambient", "0.4084"], ["ambient", "0.2770"], ["ambient", "0.3554"], ["electronic", "0.2789"], ["ambient", "0.3514"], ["experimental", "0.1484"], ["electronic", "0.1896"], ["rock", "0.2146"], ["rock", "0.2052"], ["rock", "0.2106"], ["electronic", "0.2495"], ["rock", "0.2339"]]}], "LOO3SERB14": ["LOO3SERB14", "A whole", "Loop 3 Series B", "RMR", "/media/emme/0B/DATA/rmr/processed/21_lv3/Loop 3 Series B/mp3/LV3_B_ 3-item_3.mp3", {"duration": "77.0863", "sample_rate": "44100", "sample_count": "3399505.00", "channels": "2", "bit_resolution": "16", "max_volume": "-5.2991", "mean_rms": "1787.0000", "tags_mtt": [["ambient", "0.1873"], ["slow", "0.1063"], ["classical", "0.1033"], ["choir", "0.0922"], ["quiet", "0.0873"], ["opera", "0.0840"], ["drums", "0.0840"], ["male", "0.0785"], ["weird", "0.0721"]], "tags_msd": [["ambient", "0.2104"], ["electronic", "0.1651"], ["experimental", "0.1418"], ["instrumental", "0.0972"], ["metal", "0.0907"], ["rock", "0.0895"], ["jazz", "0.0765"], ["electronica", "0.0474"], ["Progressive rock", "0.0434"]], "comp_mtt": [["male", "0.1267"], ["choir", "0.1938"], ["choir", "0.4897"], ["rock", "0.3086"], ["weird", "0.1312"], ["choir", "0.1692"], ["choir", "0.3061"], ["male", "0.1881"], ["ambient", "0.1735"], ["choir", "0.2082"], ["drums", "0.1058"], ["ambient", "0.1661"], ["opera", "0.2667"], ["classical", "0.4400"], ["techno", "0.2411"], ["drums", "0.3195"], ["classical", "0.4835"], ["classical", "0.3567"], ["quiet", "0.4133"], ["ambient", "0.4956"], ["ambient", "0.5517"], ["ambient", "0.4583"], ["ambient", "0.4756"], ["ambient", "0.4178"], ["ambient", "0.4029"]], "comp_msd": [["metal", "0.1783"], ["ambient", "0.1668"], ["experimental", "0.1175"], ["experimental", "0.1874"], ["metal", "0.2632"], ["experimental", "0.1242"], ["metal", "0.3375"], ["metal", "0.3151"], ["metal", "0.2495"], ["ambient", "0.2513"], ["rock", "0.2047"], ["ambient", "0.1833"], ["electronic", "0.2255"], ["jazz", "0.4597"], ["electronic", "0.2794"], ["ambient", "0.2744"], ["jazz", "0.2314"], ["ambient", "0.2244"], ["ambient", "0.3157"], ["ambient", "0.3570"], ["electronic", "0.3412"], ["ambient", "0.3786"], ["ambient", "0.4229"], ["ambient", "0.4427"], ["ambient", "0.4887"]]}], "LOO3SERB15": ["LOO3SERB15", "Human nature", "Loop 3 Series B", "RMR", "/media/emme/0B/DATA/rmr/processed/21_lv3/Loop 3 Series B/mp3/LV3_B_ 4-item_4.mp3", {"duration": "77.0863", "sample_rate": "44100", "sample_count": "3399505.00", "channels": "2", "bit_resolution": "16", "max_volume": "-4.3599", "mean_rms": "3805.0000", "tags_mtt": [["ambient", "0.2334"], ["weird", "0.2017"], ["electronic", "0.1337"], ["techno", "0.1221"], ["loud", "0.0874"], ["synth", "0.0790"], ["slow", "0.0611"], ["drums", "0.0553"], ["no vocals", "0.0531"]], "tags_msd": [["ambient", "0.3788"], ["experimental", "0.3122"], ["electronic", "0.2342"], ["instrumental", "0.0849"], ["metal", "0.0819"], ["electronica", "0.0648"], ["rock", "0.0645"], ["punk", "0.0388"], ["indie", "0.0382"]], "comp_mtt": [["ambient", "0.2365"], ["ambient", "0.3221"], ["ambient", "0.2129"], ["weird", "0.1425"], ["ambient", "0.3752"], ["ambient", "0.3844"], ["ambient", "0.3131"], ["ambient", "0.1754"], ["ambient", "0.2115"], ["ambient", "0.3185"], ["ambient", "0.3063"], ["weird", "0.2348"], ["weird", "0.2784"], ["weird", "0.2372"], ["weird", "0.2591"], ["ambient", "0.2408"], ["weird", "0.3028"], ["techno", "0.2912"], ["weird", "0.2820"], ["weird", "0.2063"], ["ambient", "0.3882"], ["ambient", "0.2960"], ["ambient", "0.2961"], ["ambient", "0.2514"], ["classical", "0.2957"]], "comp_msd": [["ambient", "0.4056"], ["ambient", "0.4974"], ["ambient", "0.3507"], ["ambient", "0.3688"], ["experimental", "0.3707"], ["experimental", "0.3688"], ["ambient", "0.4732"], ["ambient", "0.5505"], ["ambient", "0.5609"], ["ambient", "0.3909"], ["ambient", "0.3677"], ["ambient", "0.3815"], ["ambient", "0.5287"], ["ambient", "0.4022"], ["experimental", "0.3804"], ["ambient", "0.4598"], ["experimental", "0.3753"], ["experimental", "0.2440"], ["metal", "0.3523"], ["experimental", "0.2428"], ["ambient", "0.4599"], ["ambient", "0.4113"], ["ambient", "0.5329"], ["ambient", "0.5291"], ["electronic", "0.2306"]]}], "LOO3SERB16": ["LOO3SERB16", "Optimization in order to nudge, coax, tune, and herd behavior toward profitable outcomes", "Loop 3 Series B", "RMR", "/media/emme/0B/DATA/rmr/processed/21_lv3/Loop 3 Series B/mp3/LV3_B_ 5-item_7.mp3", {"duration": "77.0863", "sample_rate": "44100", "sample_count": "3399505.00", "channels": "2", "bit_resolution": "16", "max_volume": "-6.6316", "mean_rms": "1697.0000", "tags_mtt": [["male", "0.1505"], ["opera", "0.0993"], ["male vocal", "0.0973"], ["man", "0.0872"], ["male voice", "0.0802"], ["vocal", "0.0751"], ["techno", "0.0728"], ["drums", "0.0679"], ["electronic", "0.0646"]], "tags_msd": [["rock", "0.1547"], ["experimental", "0.1424"], ["electronic", "0.1043"], ["metal", "0.0979"], ["jazz", "0.0750"], ["Hip-Hop", "0.0735"], ["alternative", "0.0667"], ["ambient", "0.0645"], ["punk", "0.0626"]], "comp_mtt": [["drums", "0.1537"], ["ambient", "0.2080"], ["ambient", "0.1581"], ["ambient", "0.3361"], ["choir", "0.1575"], ["guitar", "0.3244"], ["opera", "0.3399"], ["techno", "0.0999"], ["male", "0.1400"], ["electronic", "0.1324"], ["male", "0.1538"], ["male", "0.2523"], ["opera", "0.2909"], ["male", "0.3250"], ["male", "0.2636"], ["male", "0.2526"], ["rock", "0.1505"], ["techno", "0.2139"], ["male", "0.1912"], ["male", "0.1157"], ["male", "0.2258"], ["opera", "0.3773"], ["male", "0.2620"], ["male", "0.2377"], ["male", "0.2888"]], "comp_msd": [["rock", "0.1824"], ["metal", "0.3126"], ["experimental", "0.2560"], ["ambient", "0.2613"], ["electronic", "0.2589"], ["rock", "0.1962"], ["rock", "0.2442"], ["rock", "0.3093"], ["rock", "0.2077"], ["rock", "0.2591"], ["rock", "0.2573"], ["rock", "0.2970"], ["jazz", "0.1981"], ["blues", "0.2367"], ["Hip-Hop", "0.2412"], ["experimental", "0.1790"], ["metal", "0.3496"], ["metal", "0.3038"], ["metal", "0.4061"], ["experimental", "0.1772"], ["Hip-Hop", "0.3685"], ["electronic", "0.2014"], ["rock", "0.1544"], ["experimental", "0.1757"], ["Hip-Hop", "0.2683"]]}], "LOO3SERBB17": ["LOO3SERBB17", "Information and a right to combat", "Loop 3 Series BB", "RMR", "/media/emme/0B/DATA/rmr/processed/21_lv3/Loop 3 Series BB/mp3/LV3_BB_ 1-item_0.mp3", {"duration": "85.0798", "sample_rate": "44100", "sample_count": "3752018.00", "channels": "2", "bit_resolution": "16", "max_volume": "-2.9656", "mean_rms": "7122.0000", "tags_mtt": [["ambient", "0.2856"], ["weird", "0.1312"], ["slow", "0.1154"], ["electronic", "0.0984"], ["synth", "0.0781"], ["loud", "0.0771"], ["techno", "0.0497"], ["no vocals", "0.0458"], ["guitar", "0.0434"]], "tags_msd": [["ambient", "0.3686"], ["electronic", "0.2635"], ["experimental", "0.2632"], ["indie", "0.0881"], ["instrumental", "0.0871"], ["metal", "0.0826"], ["rock", "0.0781"], ["electronica", "0.0721"], ["alternative", "0.0580"]], "comp_mtt": [["ambient", "0.2009"], ["ambient", "0.2506"], ["ambient", "0.2385"], ["ambient", "0.1753"], ["ambient", "0.2419"], ["ambient", "0.3922"], ["ambient", "0.3570"], ["ambient", "0.1964"], ["ambient", "0.2800"], ["ambient", "0.3288"], ["ambient", "0.4043"], ["ambient", "0.3513"], ["ambient", "0.2672"], ["loud", "0.2144"], ["loud", "0.2488"], ["loud", "0.2045"], ["ambient", "0.1714"], ["ambient", "0.3027"], ["ambient", "0.2333"], ["ambient", "0.2630"], ["ambient", "0.4468"], ["ambient", "0.3502"], ["ambient", "0.4965"], ["ambient", "0.3263"], ["ambient", "0.4385"], ["ambient", "0.3407"], ["ambient", "0.2408"], ["guitar", "0.2470"]], "comp_msd": [["electronic", "0.3522"], ["metal", "0.4373"], ["metal", "0.3192"], ["metal", "0.3224"], ["metal", "0.3566"], ["ambient", "0.4117"], ["ambient", "0.4374"], ["experimental", "0.3107"], ["experimental", "0.3481"], ["ambient", "0.4341"], ["ambient", "0.3911"], ["ambient", "0.4222"], ["ambient", "0.4621"], ["experimental", "0.4064"], ["electronic", "0.4525"], ["electronic", "0.4237"], ["ambient", "0.4446"], ["ambient", "0.4607"], ["ambient", "0.4485"], ["electronic", "0.4279"], ["ambient", "0.5656"], ["ambient", "0.4856"], ["ambient", "0.4617"], ["ambient", "0.3297"], ["ambient", "0.4058"], ["ambient", "0.3272"], ["experimental", "0.3463"], ["experimental", "0.3268"]]}], "LOO3SERBB18": ["LOO3SERBB18", "Danger of the peasant or farmer", "Loop 3 Series BB", "RMR", "/media/emme/0B/DATA/rmr/processed/21_lv3/Loop 3 Series BB/mp3/LV3_BB_ 2-item_1.mp3", {"duration": "85.0798", "sample_rate": "44100", "sample_count": "3752018.00", "channels": "2", "bit_resolution": "16", "max_volume": "-0.9903", "mean_rms": "7100.0000", "tags_mtt": [["rock", "0.2422"], ["loud", "0.1936"], ["weird", "0.1130"], ["drums", "0.1094"], ["techno", "0.1065"], ["electronic", "0.0959"], ["guitar", "0.0922"], ["male", "0.0904"], ["ambient", "0.0852"]], "tags_msd": [["experimental", "0.2249"], ["rock", "0.1573"], ["electronic", "0.1358"], ["metal", "0.1232"], ["ambient", "0.0981"], ["indie", "0.0701"], ["alternative", "0.0642"], ["punk", "0.0595"], ["instrumental", "0.0556"]], "comp_mtt": [["drums", "0.1850"], ["weird", "0.1465"], ["rock", "0.2169"], ["ambient", "0.1656"], ["classical", "0.2056"], ["classical", "0.2338"], ["rock", "0.3236"], ["male", "0.2587"], ["rock", "0.3249"], ["rock", "0.3445"], ["rock", "0.4899"], ["rock", "0.3340"], ["loud", "0.2442"], ["drums", "0.1745"], ["rock", "0.3571"], ["rock", "0.2687"], ["rock", "0.3876"], ["rock", "0.3663"], ["rock", "0.1673"], ["rock", "0.4425"], ["rock", "0.4269"], ["loud", "0.4729"], ["loud", "0.3351"], ["techno", "0.3976"], ["loud", "0.3422"], ["loud", "0.3377"], ["ambient", "0.2856"], ["techno", "0.3201"]], "comp_msd": [["rock", "0.1992"], ["metal", "0.3344"], ["metal", "0.2576"], ["rock", "0.2381"], ["rock", "0.2405"], ["rock", "0.3503"], ["rock", "0.1991"], ["rock", "0.2770"], ["rock", "0.2570"], ["metal", "0.1808"], ["experimental", "0.1875"], ["metal", "0.2355"], ["experimental", "0.4006"], ["experimental", "0.3489"], ["rock", "0.1568"], ["electronic", "0.1844"], ["rock", "0.1699"], ["metal", "0.1490"], ["electronic", "0.1812"], ["experimental", "0.2406"], ["experimental", "0.2610"], ["experimental", "0.3108"], ["experimental", "0.3205"], ["experimental", "0.3978"], ["experimental", "0.3736"], ["experimental", "0.4353"], ["experimental", "0.4221"], ["experimental", "0.4212"]]}], "LOO3SERBB19": ["LOO3SERBB19", "Rooms that would entail frantic entrepreneurial activity", "Loop 3 Series BB", "RMR", "/media/emme/0B/DATA/rmr/processed/21_lv3/Loop 3 Series BB/mp3/LV3_BB_ 3-item_2.mp3", {"duration": "85.0798", "sample_rate": "44100", "sample_count": "3752018.00", "channels": "2", "bit_resolution": "16", "max_volume": "-5.0344", "mean_rms": "3555.0000", "tags_mtt": [["ambient", "0.2074"], ["weird", "0.1330"], ["electronic", "0.0960"], ["slow", "0.0750"], ["techno", "0.0696"], ["synth", "0.0598"], ["rock", "0.0547"], ["loud", "0.0521"], ["male", "0.0431"]], "tags_msd": [["experimental", "0.2151"], ["ambient", "0.2100"], ["metal", "0.1671"], ["electronic", "0.1152"], ["rock", "0.1141"], ["instrumental", "0.0895"], ["punk", "0.0815"], ["alternative", "0.0533"], ["indie", "0.0490"]], "comp_mtt": [["ambient", "0.1491"], ["ambient", "0.1836"], ["ambient", "0.2029"], ["ambient", "0.2307"], ["ambient", "0.1692"], ["ambient", "0.2438"], ["ambient", "0.3590"], ["ambient", "0.3209"], ["ambient", "0.3694"], ["ambient", "0.2790"], ["ambient", "0.3737"], ["ambient", "0.3052"], ["ambient", "0.1768"], ["male", "0.2429"], ["rock", "0.1857"], ["ambient", "0.2196"], ["rock", "0.1629"], ["weird", "0.2169"], ["ambient", "0.2065"], ["ambient", "0.1727"], ["weird", "0.2474"], ["weird", "0.2136"], ["weird", "0.1991"], ["ambient", "0.1966"], ["ambient", "0.2022"], ["ambient", "0.2036"], ["quiet", "0.1998"], ["quiet", "0.2943"]], "comp_msd": [["ambient", "0.3418"], ["metal", "0.3139"], ["metal", "0.2583"], ["metal", "0.2400"], ["metal", "0.2293"], ["rock", "0.2274"], ["ambient", "0.3339"], ["experimental", "0.2975"], ["experimental", "0.2976"], ["metal", "0.2568"], ["experimental", "0.2086"], ["punk", "0.2120"], ["experimental", "0.1972"], ["rock", "0.2077"], ["metal", "0.2479"], ["metal", "0.2261"], ["experimental", "0.2121"], ["metal", "0.2451"], ["experimental", "0.2103"], ["experimental", "0.2706"], ["metal", "0.2720"], ["experimental", "0.3177"], ["metal", "0.2888"], ["ambient", "0.4253"], ["ambient", "0.3166"], ["ambient", "0.3713"], ["ambient", "0.3109"], ["experimental", "0.1844"]]}], "LOO3SERBB20": ["LOO3SERBB20", "A way that a religion", "Loop 3 Series BB", "RMR", "/media/emme/0B/DATA/rmr/processed/21_lv3/Loop 3 Series BB/mp3/LV3_BB_ 4-item_3.mp3", {"duration": "85.0798", "sample_rate": "44100", "sample_count": "3752018.00", "channels": "2", "bit_resolution": "16", "max_volume": "-4.8291", "mean_rms": "4068.0000", "tags_mtt": [["ambient", "0.2093"], ["drums", "0.1428"], ["electronic", "0.1370"], ["techno", "0.1362"], ["weird", "0.1228"], ["slow", "0.0970"], ["synth", "0.0688"], ["beat", "0.0659"], ["male", "0.0582"]], "tags_msd": [["electronic", "0.2453"], ["ambient", "0.2265"], ["experimental", "0.1873"], ["metal", "0.1044"], ["rock", "0.0980"], ["electronica", "0.0737"], ["alternative", "0.0548"], ["instrumental", "0.0544"], ["jazz", "0.0474"]], "comp_mtt": [["ambient", "0.2072"], ["ambient", "0.4559"], ["ambient", "0.5757"], ["ambient", "0.6854"], ["ambient", "0.2538"], ["techno", "0.2052"], ["drums", "0.2473"], ["male", "0.2387"], ["ambient", "0.2954"], ["ambient", "0.1722"], ["ambient", "0.2586"], ["electronic", "0.2823"], ["weird", "0.2015"], ["ambient", "0.2084"], ["ambient", "0.3280"], ["electronic", "0.3743"], ["techno", "0.5260"], ["drums", "0.3237"], ["ambient", "0.2564"], ["weird", "0.1999"], ["weird", "0.1759"], ["weird", "0.1414"], ["drums", "0.3865"], ["drums", "0.1833"], ["techno", "0.4344"], ["guitar", "0.2627"], ["drums", "0.4282"], ["quiet", "0.2655"]], "comp_msd": [["ambient", "0.3173"], ["ambient", "0.4438"], ["ambient", "0.5324"], ["ambient", "0.5548"], ["ambient", "0.1928"], ["experimental", "0.1884"], ["ambient", "0.1865"], ["electronic", "0.2004"], ["ambient", "0.3109"], ["experimental", "0.2753"], ["ambient", "0.2705"], ["rock", "0.1479"], ["metal", "0.4230"], ["electronic", "0.3414"], ["electronic", "0.3940"], ["electronic", "0.4027"], ["electronic", "0.4365"], ["ambient", "0.4452"], ["electronic", "0.3676"], ["metal", "0.4504"], ["electronic", "0.3038"], ["electronic", "0.4368"], ["electronic", "0.3844"], ["electronic", "0.2921"], ["electronic", "0.2384"], ["jazz", "0.1756"], ["metal", "0.2886"], ["rock", "0.2349"]]}], "LOO3SERBB21": ["LOO3SERBB21", "Massive influx", "Loop 3 Series BB", "RMR", "/media/emme/0B/DATA/rmr/processed/21_lv3/Loop 3 Series BB/mp3/LV3_BB_ 5-item_4.mp3", {"duration": "85.0798", "sample_rate": "44100", "sample_count": "3752018.00", "channels": "2", "bit_resolution": "16", "max_volume": "-5.3329", "mean_rms": "3821.0000", "tags_mtt": [["ambient", "0.3075"], ["weird", "0.1945"], ["electronic", "0.1604"], ["techno", "0.1168"], ["synth", "0.0984"], ["slow", "0.0909"], ["no vocals", "0.0489"], ["new age", "0.0430"], ["loud", "0.0392"]], "tags_msd": [["ambient", "0.3416"], ["experimental", "0.2848"], ["electronic", "0.2185"], ["instrumental", "0.0844"], ["rock", "0.0735"], ["electronica", "0.0595"], ["metal", "0.0548"], ["indie", "0.0420"], ["alternative", "0.0414"]], "comp_mtt": [["choir", "0.2488"], ["ambient", "0.3493"], ["ambient", "0.2388"], ["ambient", "0.4513"], ["ambient", "0.2354"], ["ambient", "0.1803"], ["ambient", "0.2486"], ["ambient", "0.4888"], ["ambient", "0.2401"], ["ambient", "0.3455"], ["ambient", "0.3718"], ["ambient", "0.3099"], ["ambient", "0.4048"], ["ambient", "0.2986"], ["electronic", "0.3057"], ["ambient", "0.4360"], ["ambient", "0.3160"], ["electronic", "0.1814"], ["ambient", "0.3000"], ["ambient", "0.2278"], ["techno", "0.5112"], ["weird", "0.3466"], ["weird", "0.2975"], ["ambient", "0.2481"], ["ambient", "0.3748"], ["ambient", "0.4320"], ["ambient", "0.3329"], ["ambient", "0.4527"]], "comp_msd": [["ambient", "0.3721"], ["ambient", "0.4603"], ["ambient", "0.2555"], ["ambient", "0.2756"], ["ambient", "0.2829"], ["ambient", "0.2978"], ["ambient", "0.3059"], ["ambient", "0.3862"], ["ambient", "0.3172"], ["ambient", "0.3655"], ["ambient", "0.4568"], ["ambient", "0.4311"], ["ambient", "0.3557"], ["experimental", "0.2626"], ["experimental", "0.2853"], ["ambient", "0.3805"], ["ambient", "0.3315"], ["experimental", "0.2880"], ["experimental", "0.3331"], ["experimental", "0.2849"], ["electronic", "0.2432"], ["ambient", "0.3256"], ["experimental", "0.3608"], ["ambient", "0.4447"], ["ambient", "0.5363"], ["ambient", "0.3886"], ["experimental", "0.4179"], ["ambient", "0.4550"]]}], "LOO3SERBB22": ["LOO3SERBB22", "Not volatile but voluntative", "Loop 3 Series BB", "RMR", "/media/emme/0B/DATA/rmr/processed/21_lv3/Loop 3 Series BB/mp3/LV3_BB_ 6-item_6.mp3", {"duration": "85.0798", "sample_rate": "44100", "sample_count": "3752018.00", "channels": "2", "bit_resolution": "16", "max_volume": "-0.9108", "mean_rms": "4598.0000", "tags_mtt": [["techno", "0.2256"], ["drums", "0.1856"], ["electronic", "0.1669"], ["rock", "0.1350"], ["weird", "0.1111"], ["fast", "0.1074"], ["ambient", "0.1053"], ["beat", "0.0951"], ["loud", "0.0786"]], "tags_msd": [["electronic", "0.2461"], ["experimental", "0.2253"], ["ambient", "0.1411"], ["metal", "0.1333"], ["rock", "0.1222"], ["electronica", "0.0782"], ["alternative", "0.0657"], ["instrumental", "0.0617"], ["indie", "0.0577"]], "comp_mtt": [["drums", "0.1531"], ["rock", "0.3002"], ["ambient", "0.2771"], ["ambient", "0.2070"], ["drums", "0.3478"], ["ambient", "0.4188"], ["techno", "0.1930"], ["drums", "0.3935"], ["weird", "0.2772"], ["techno", "0.4311"], ["techno", "0.5325"], ["rock", "0.4885"], ["techno", "0.3335"], ["rock", "0.4374"], ["techno", "0.4276"], ["techno", "0.5565"], ["techno", "0.3900"], ["rock", "0.4355"], ["drums", "0.2767"], ["techno", "0.3110"], ["techno", "0.3598"], ["electronic", "0.1914"], ["electronic", "0.1322"], ["quiet", "0.1763"], ["electronic", "0.1987"], ["electronic", "0.1290"], ["opera", "0.1218"], ["techno", "0.1292"]], "comp_msd": [["electronic", "0.2051"], ["metal", "0.3492"], ["ambient", "0.2440"], ["metal", "0.2618"], ["experimental", "0.2361"], ["ambient", "0.4192"], ["experimental", "0.2990"], ["electronic", "0.3085"], ["electronic", "0.2558"], ["experimental", "0.4032"], ["electronic", "0.4373"], ["metal", "0.2904"], ["electronic", "0.3312"], ["metal", "0.4712"], ["electronic", "0.3613"], ["experimental", "0.3030"], ["metal", "0.2880"], ["experimental", "0.2879"], ["electronic", "0.3374"], ["electronic", "0.4048"], ["electronic", "0.3688"], ["electronic", "0.2684"], ["rock", "0.2386"], ["rock", "0.2384"], ["rock", "0.2253"], ["rock", "0.3075"], ["rock", "0.2610"], ["rock", "0.1898"]]}], "LOO3SERC23": ["LOO3SERC23", "Human behaviors those programs encourage", "Loop 3 Series C", "RMR", "/media/emme/0B/DATA/rmr/processed/21_lv3/Loop 3 Series C/mp3/LV3_C_ 1-item_3.mp3", {"duration": "77.0863", "sample_rate": "44100", "sample_count": "3399505.00", "channels": "2", "bit_resolution": "16", "max_volume": "-0.9684", "mean_rms": "5768.0000", "tags_mtt": [["rock", "0.2040"], ["techno", "0.1911"], ["electronic", "0.1623"], ["drums", "0.1560"], ["loud", "0.1506"], ["weird", "0.1487"], ["ambient", "0.0966"], ["guitar", "0.0941"], ["beat", "0.0891"]], "tags_msd": [["metal", "0.2058"], ["experimental", "0.2014"], ["electronic", "0.1522"], ["ambient", "0.1184"], ["rock", "0.1150"], ["instrumental", "0.0664"], ["alternative", "0.0591"], ["punk", "0.0558"], ["indie", "0.0524"]], "comp_mtt": [["rock", "0.1327"], ["ambient", "0.2085"], ["rock", "0.1929"], ["rock", "0.3430"], ["rock", "0.4541"], ["loud", "0.3165"], ["techno", "0.3313"], ["rock", "0.2404"], ["rock", "0.3722"], ["weird", "0.2395"], ["loud", "0.3504"], ["loud", "0.3070"], ["techno", "0.4395"], ["techno", "0.2956"], ["loud", "0.3528"], ["rock", "0.3913"], ["techno", "0.3019"], ["drums", "0.3821"], ["drums", "0.2930"], ["drums", "0.3772"], ["drums", "0.3774"], ["drums", "0.5091"], ["rock", "0.2657"], ["drums", "0.2223"], ["rock", "0.3553"]], "comp_msd": [["metal", "0.2944"], ["metal", "0.2770"], ["metal", "0.2358"], ["metal", "0.3595"], ["metal", "0.4181"], ["experimental", "0.2940"], ["metal", "0.3905"], ["metal", "0.5757"], ["metal", "0.5804"], ["experimental", "0.3204"], ["experimental", "0.3138"], ["experimental", "0.3761"], ["rock", "0.2932"], ["experimental", "0.2202"], ["experimental", "0.3906"], ["metal", "0.2301"], ["experimental", "0.1976"], ["electronic", "0.2317"], ["electronic", "0.2600"], ["electronic", "0.3320"], ["electronic", "0.3314"], ["electronic", "0.3033"], ["electronic", "0.2924"], ["rock", "0.2257"], ["rock", "0.2329"]]}], "LOO3SERE24": ["LOO3SERE24", "A medium of action", "Loop 3 Series E", "RMR", "/media/emme/0B/DATA/rmr/processed/21_lv3/Loop 3 Series E/mp3/LV3_E_ 1-item_2.mp3", {"duration": "77.0863", "sample_rate": "44100", "sample_count": "3399505.00", "channels": "2", "bit_resolution": "16", "max_volume": "-1.8019", "mean_rms": "5143.0000", "tags_mtt": [["ambient", "0.2569"], ["techno", "0.1652"], ["electronic", "0.1621"], ["weird", "0.1560"], ["drums", "0.1371"], ["slow", "0.0983"], ["synth", "0.0950"], ["rock", "0.0915"], ["loud", "0.0766"]], "tags_msd": [["ambient", "0.2729"], ["electronic", "0.2519"], ["experimental", "0.2469"], ["metal", "0.1197"], ["rock", "0.0903"], ["instrumental", "0.0830"], ["electronica", "0.0737"], ["alternative", "0.0515"], ["indie", "0.0458"]], "comp_mtt": [["ambient", "0.3024"], ["ambient", "0.5116"], ["ambient", "0.3860"], ["ambient", "0.3164"], ["ambient", "0.1957"], ["techno", "0.2260"], ["techno", "0.3016"], ["drums", "0.3296"], ["drums", "0.2786"], ["techno", "0.4184"], ["rock", "0.2415"], ["electronic", "0.2399"], ["ambient", "0.3304"], ["drums", "0.3302"], ["ambient", "0.4687"], ["ambient", "0.3088"], ["ambient", "0.5013"], ["ambient", "0.4925"], ["ambient", "0.4597"], ["ambient", "0.2226"], ["ambient", "0.2417"], ["rock", "0.4439"], ["techno", "0.5933"], ["ambient", "0.3139"], ["techno", "0.2148"]], "comp_msd": [["electronic", "0.2834"], ["ambient", "0.4166"], ["ambient", "0.4131"], ["experimental", "0.3047"], ["electronic", "0.2833"], ["electronic", "0.2934"], ["electronic", "0.3444"], ["electronic", "0.2619"], ["metal", "0.2327"], ["experimental", "0.3479"], ["experimental", "0.2541"], ["experimental", "0.3391"], ["ambient", "0.2726"], ["ambient", "0.3368"], ["metal", "0.1966"], ["ambient", "0.3506"], ["ambient", "0.4797"], ["ambient", "0.5582"], ["ambient", "0.4432"], ["ambient", "0.3186"], ["electronic", "0.2644"], ["metal", "0.5590"], ["experimental", "0.2675"], ["electronic", "0.2860"], ["electronic", "0.3642"]]}], "LOO3SERE25": ["LOO3SERE25", "Future in a system which is extremely short", "Loop 3 Series E", "RMR", "/media/emme/0B/DATA/rmr/processed/21_lv3/Loop 3 Series E/mp3/LV3_E_ 2-item_4.mp3", {"duration": "77.0863", "sample_rate": "44100", "sample_count": "3399505.00", "channels": "2", "bit_resolution": "16", "max_volume": "-3.6752", "mean_rms": "5426.0000", "tags_mtt": [["rock", "0.3065"], ["loud", "0.1704"], ["techno", "0.1393"], ["weird", "0.1372"], ["electronic", "0.1365"], ["guitar", "0.1294"], ["metal", "0.1170"], ["ambient", "0.1038"], ["drums", "0.0731"]], "tags_msd": [["metal", "0.2176"], ["experimental", "0.1644"], ["rock", "0.1252"], ["punk", "0.1027"], ["ambient", "0.0747"], ["electronic", "0.0729"], ["instrumental", "0.0592"], ["alternative", "0.0519"], ["heavy metal", "0.0511"]], "comp_mtt": [["electronic", "0.2304"], ["ambient", "0.2626"], ["ambient", "0.1840"], ["ambient", "0.0732"], ["weird", "0.0782"], ["ambient", "0.2602"], ["ambient", "0.2175"], ["rock", "0.2094"], ["drums", "0.2278"], ["rock", "0.5405"], ["rock", "0.4197"], ["rock", "0.2967"], ["rock", "0.3169"], ["rock", "0.4115"], ["rock", "0.5793"], ["rock", "0.3150"], ["rock", "0.3073"], ["weird", "0.1998"], ["rock", "0.4522"], ["techno", "0.2764"], ["rock", "0.7672"], ["rock", "0.7618"], ["rock", "0.6729"], ["rock", "0.6580"], ["techno", "0.4857"]], "comp_msd": [["experimental", "0.2607"], ["experimental", "0.2194"], ["metal", "0.2338"], ["metal", "0.2324"], ["metal", "0.3530"], ["rock", "0.1948"], ["rock", "0.1669"], ["experimental", "0.1819"], ["experimental", "0.1946"], ["metal", "0.3081"], ["metal", "0.3608"], ["metal", "0.4234"], ["metal", "0.2100"], ["experimental", "0.2740"], ["punk", "0.2746"], ["experimental", "0.2255"], ["metal", "0.2891"], ["metal", "0.1905"], ["metal", "0.3121"], ["metal", "0.2244"], ["metal", "0.2478"], ["metal", "0.2482"], ["experimental", "0.2775"], ["metal", "0.2952"], ["experimental", "0.2085"]]}], "LOO3SERE26": ["LOO3SERE26", "A retranscription", "Loop 3 Series E", "RMR", "/media/emme/0B/DATA/rmr/processed/21_lv3/Loop 3 Series E/mp3/LV3_E_ 3-item_5.mp3", {"duration": "77.0863", "sample_rate": "44100", "sample_count": "3399505.00", "channels": "2", "bit_resolution": "16", "max_volume": "-3.7056", "mean_rms": "3628.0000", "tags_mtt": [["rock", "0.5680"], ["guitar", "0.3559"], ["metal", "0.2451"], ["drums", "0.1759"], ["loud", "0.1217"], ["fast", "0.0816"], ["male", "0.0560"], ["vocal", "0.0459"], ["male vocal", "0.0439"]], "tags_msd": [["rock", "0.1866"], ["punk", "0.1646"], ["metal", "0.1594"], ["experimental", "0.1175"], ["heavy metal", "0.0834"], ["hard rock", "0.0652"], ["alternative", "0.0606"], ["indie", "0.0563"], ["instrumental", "0.0521"]], "comp_mtt": [["loud", "0.1244"], ["loud", "0.1103"], ["ambient", "0.1392"], ["rock", "0.3058"], ["rock", "0.7921"], ["rock", "0.8837"], ["rock", "0.9050"], ["rock", "0.8730"], ["rock", "0.8235"], ["rock", "0.7376"], ["rock", "0.7876"], ["rock", "0.7748"], ["rock", "0.7751"], ["rock", "0.8148"], ["rock", "0.7170"], ["rock", "0.8515"], ["female", "0.3035"], ["male", "0.1895"], ["ambient", "0.1610"], ["rock", "0.7956"], ["rock", "0.5892"], ["guitar", "0.4727"], ["rock", "0.5895"], ["rock", "0.6259"], ["rock", "0.6032"]], "comp_msd": [["metal", "0.1922"], ["heavy metal", "0.2013"], ["metal", "0.1865"], ["metal", "0.2975"], ["rock", "0.2658"], ["rock", "0.2875"], ["heavy metal", "0.2505"], ["rock", "0.2581"], ["rock", "0.2145"], ["punk", "0.2220"], ["punk", "0.3053"], ["punk", "0.3189"], ["punk", "0.3321"], ["punk", "0.3060"], ["punk", "0.2097"], ["experimental", "0.2480"], ["blues", "0.1627"], ["country", "0.2197"], ["rock", "0.2289"], ["rock", "0.2607"], ["punk", "0.3213"], ["rock", "0.1750"], ["metal", "0.3057"], ["metal", "0.1539"], ["rock", "0.1891"]]}], "LOO3SERE27": ["LOO3SERE27", "A resonance chamber", "Loop 3 Series E", "RMR", "/media/emme/0B/DATA/rmr/processed/21_lv3/Loop 3 Series E/mp3/LV3_E_ 4-item_6.mp3", {"duration": "77.0863", "sample_rate": "44100", "sample_count": "3399505.00", "channels": "2", "bit_resolution": "16", "max_volume": "-0.9838", "mean_rms": "5935.0000", "tags_mtt": [["ambient", "0.1627"], ["techno", "0.1529"], ["electronic", "0.1460"], ["weird", "0.1278"], ["rock", "0.1173"], ["drums", "0.0923"], ["male", "0.0892"], ["slow", "0.0883"], ["guitar", "0.0794"]], "tags_msd": [["experimental", "0.2143"], ["ambient", "0.1678"], ["electronic", "0.1608"], ["rock", "0.1256"], ["metal", "0.1196"], ["instrumental", "0.0743"], ["indie", "0.0700"], ["alternative", "0.0674"], ["electronica", "0.0459"]], "comp_mtt": [["ambient", "0.1854"], ["ambient", "0.3487"], ["ambient", "0.3794"], ["ambient", "0.4610"], ["ambient", "0.4961"], ["techno", "0.1509"], ["ambient", "0.3284"], ["techno", "0.3166"], ["techno", "0.2879"], ["rock", "0.3014"], ["weird", "0.1664"], ["rock", "0.2674"], ["techno", "0.4017"], ["techno", "0.2066"], ["techno", "0.1971"], ["male", "0.3018"], ["techno", "0.2464"], ["techno", "0.2825"], ["rock", "0.3676"], ["ambient", "0.2135"], ["male", "0.1576"], ["electronic", "0.2167"], ["loud", "0.2217"], ["ambient", "0.2045"], ["guitar", "0.1757"]], "comp_msd": [["experimental", "0.2616"], ["ambient", "0.3195"], ["ambient", "0.3283"], ["ambient", "0.2932"], ["ambient", "0.3916"], ["electronic", "0.1590"], ["ambient", "0.3623"], ["metal", "0.3145"], ["experimental", "0.1911"], ["electronic", "0.2942"], ["metal", "0.1483"], ["metal", "0.3400"], ["experimental", "0.2811"], ["metal", "0.2091"], ["metal", "0.2453"], ["experimental", "0.2069"], ["experimental", "0.2040"], ["experimental", "0.2590"], ["rock", "0.2250"], ["experimental", "0.2403"], ["experimental", "0.2420"], ["experimental", "0.3102"], ["experimental", "0.3259"], ["ambient", "0.3017"], ["rock", "0.2009"]]}]}